{    
"name": "Warding Candle",    
"icon": "amethyst_imbuement:warding_candle",    
"category": "amethyst_imbuement:imbuing",    
"pages": [        
{            
"type": "patchouli:text",            
"text": "Warding Candle"
},
{
"type": "amethyst_imbuement:imbuing_recipe",
"title": "Warding Candle Imbuing",
"imbue_a_item": "amethyst_imbuement:smoky_quartz",
"imbue_b_item": "amethyst_imbuement:smoky_quartz",
"imbue_c_item": "amethyst_imbuement:smoky_quartz",
"imbue_d_item": "amethyst_imbuement:smoky_quartz",
"craft_a_item": "minecraft:candle",
"craft_b_item": "minecraft:candle",
"craft_c_item": "minecraft:candle",
"craft_d_item": "minecraft:candle",
"craft_e_item": "minecraft:obsidian",
"craft_f_item": "minecraft:candle",
"craft_g_item": "minecraft:candle",
"craft_h_item": "minecraft:candle",
"craft_i_item": "minecraft:candle",
"cost_text": "$(l)Level Cost: $(2)3$()"
}
]
}