{
  "type": "amethyst_imbuement:imbuing",
  "imbueA": {
	"item": "amethyst_imbuement:imbued_quartz"
  },
  "imbueB": {
	"item": "amethyst_imbuement:imbued_quartz"
  },
  "imbueC": {
	"item": "amethyst_imbuement:imbued_quartz"
  },
  "imbueD": {
	"item": "amethyst_imbuement:imbued_quartz"
  },
  "craftB": {
	"item": "minecraft:milk_bucket"
  },
  "craftD": {
	"item": "minecraft:milk_bucket"
  },
  "craftF": {
	"item": "minecraft:milk_bucket"
  },
  "craftH": {
	"item": "minecraft:milk_bucket"
  },
  "title": "Cleanse",
  "cost": 8,
  "augment": "amethyst_imbuement:cleanse"
}

