{    
"name": "Regenerate Augment",    
"icon": "amethyst_imbuement:book_of_lore",    
"category": "amethyst_imbuement:scepter_available_augments",    
"pages": [        
{            
"type": "patchouli:text",            
"text": "$(l)Effect:$() Bathes you or a nearby target in an aura that heals over time.$(br)$(l)Magical School:$() $(9)Grace$()$(br)$(l)Mana Cost:$() 24$(br)$(l)Cooldown:$() 40.0 seconds$(br)$(l)Enchants:$() $(l:amethyst_imbuement:scepters/opaline_scepter)Opaline Scepter$(), $(l:amethyst_imbuement:scepters/iridescent_scepter)Iridescent Scepter$(), $(l:amethyst_imbuement:scepters/lustrous_scepter)Lustrous Scepter$()$(br)$(l)Tier:$() 1"
},
{
"type": "amethyst_imbuement:imbuing_recipe",
"title": "Regenerate Imbuing",
"anchor": "regenerate",
"imbue_a_item": "amethyst_imbuement:imbued_quartz",
"imbue_b_item": "amethyst_imbuement:imbued_quartz",
"imbue_c_item": "amethyst_imbuement:imbued_quartz",
"imbue_d_item": "amethyst_imbuement:imbued_quartz",
"craft_a_item": "minecraft:air",
"craft_b_item": "minecraft:ghast_tear",
"craft_c_item": "minecraft:air",
"craft_d_item": "minecraft:ghast_tear",
"craft_e_item": "amethyst_imbuement:opaline_scepter,amethyst_imbuement:iridescent_scepter,amethyst_imbuement:lustrous_scepter",
"craft_f_item": "minecraft:ghast_tear",
"craft_g_item": "minecraft:air",
"craft_h_item": "minecraft:ghast_tear",
"craft_i_item": "minecraft:air",
"result_item": "minecraft:enchanted_book{StoredEnchantments:[{id:\"amethyst_imbuement:regenerate\",lvl:1}]}",
"cost_text": "$(l)Level Cost: $(2)9$()"
}
]
}