{
  "name": "Bardic Scepter",
  "icon": "amethyst_imbuement:bardic_scepter",
  "category": "amethyst_imbuement:scepters",
  "sortnum": 25,
  "pages": [
    {
      "type": "patchouli:text",
      "text": "Tier two grace aspect scepter. Adds the modifiers $(l:amethyst_imbuement:modifiers/healers_grace)Healers Grace$() and $(l:amethyst_imbuement:modifiers/healers_pact)Healers Pact$() and the unique spell Inspiring Song. Can be augmented with tier two or lower spells. Second tier of progression on the $(l:amethyst_imbuement:scepter_paths/path_of_redemption)Path of Redemption.$()$(br2)$(l)Mana:$() 550"
    },
    {
      "type": "amethyst_imbuement:scepter_lineage_tier_2",
      "anc_a": "amethyst_imbuement:enduring_scepter{modifiers:[{modifier_id:\"amethyst_imbuement:lesser_enduring\"}]}",
      "anc_b": "amethyst_imbuement:graceful_scepter{modifiers:[{modifier_id:\"amethyst_imbuement:graceful\"}]}",
      "input_item": "amethyst_imbuement:bardic_scepter{modifiers:[{modifier_id:\"amethyst_core:attuned\"},{modifier_id:\"amethyst_imbuement:lesser_enduring\"}]}",
      "desc_a": "amethyst_imbuement:redemption{modifiers:[{modifier_id:\"amethyst_imbuement:healers_grace\"},{modifier_id:\"amethyst_imbuement:healers_pact\"},{modifier_id:\"amethyst_imbuement:lesser_enduring\"}]}"
    },
    {
      "type": "amethyst_imbuement:imbuing_recipe",
      "title": "Bardic Scepter",
      "imbue_a_item": "minecraft:gold_ingot",
      "imbue_b_item": "amethyst_imbuement:inquisitive_gem",
      "imbue_c_item": "minecraft:gold_ingot",
      "imbue_d_item": "minecraft:gold_ingot",
      "craft_a_item": "tag:minecraft:music_discs",
      "craft_b_item": "amethyst_imbuement:imbued_quartz",
      "craft_c_item": "amethyst_imbuement:iridescent_orb",
      "craft_d_item": "amethyst_imbuement:imbued_lapis",
      "craft_e_item": "tag:amethyst_imbuement:grace_scepters",
      "craft_f_item": "amethyst_imbuement:imbued_lapis",
      "craft_g_item": "tag:minecraft:music_discs",
      "craft_h_item": "amethyst_imbuement:imbued_quartz",
      "craft_i_item": "tag:minecraft:music_discs",
      "result_item": "amethyst_imbuement:bardic_scepter{modifiers:[{modifier_id:\"amethyst_core:attuned\"},{modifier_id:\"amethyst_imbuement:lesser_enduring\"}]}",
      "cost_text": "$(l)Level Cost: $(2)13$()"
    }
  ]
}
