{
  "type": "amethyst_imbuement:imbuing",
  "imbueA": {
	"item": "amethyst_imbuement:opal"
  },
  "imbueB": {
	"item": "amethyst_imbuement:imbued_lapis"
  },
  "imbueC": {
	"item": "amethyst_imbuement:imbued_lapis"
  },
  "imbueD": {
	"item": "amethyst_imbuement:imbued_lapis"
  },
  "craftB": {
	"item": "amethyst_imbuement:book_of_lore"
  },
  "craftD": {
	"item": "amethyst_imbuement:hard_light_block"
  },
  "craftF": {
	"item": "amethyst_imbuement:hard_light_block"
  },
  "craftH": {
	"item": "amethyst_imbuement:hard_light_block"
  },
  "title": "Hard Light Bridge",
  "cost": 11,
  "augment": "amethyst_imbuement:hard_light_bridge"
}

