{
  "type": "amethyst_imbuement:imbuing",
  "imbueA": {
	"item": "amethyst_imbuement:garnet"
  },
  "imbueB": {
	"item": "amethyst_imbuement:garnet"
  },
  "imbueC": {
	"item": "amethyst_imbuement:garnet"
  },
  "imbueD": {
	"item": "amethyst_imbuement:garnet"
  },
  "craftA": {
	"tag": "c:steel_ingots"
  },
  "craftB": {
	"item": "minecraft:blaze_powder"
  },
  "craftC": {
	"tag": "c:steel_ingots"
  },
  "craftD": {
	"item": "minecraft:blaze_powder"
  },
  "craftF": {
	"item": "minecraft:blaze_powder"
  },
  "craftG": {
	"tag": "c:steel_ingots"
  },
  "craftH": {
	"item": "minecraft:blaze_powder"
  },
  "craftI": {
	"tag": "c:steel_ingots"
  },
  "title": "Strength",
  "cost": 11,
  "augment": "amethyst_imbuement:strength"
}

